adafruit_guvx_i2c.py
adafruit_circuitpython_guvx_i2c-1.0.12.dist-info/licenses/LICENSE
adafruit_circuitpython_guvx_i2c-1.0.12.dist-info/METADATA
adafruit_circuitpython_guvx_i2c-1.0.12.dist-info/WHEEL
adafruit_circuitpython_guvx_i2c-1.0.12.dist-info/top_level.txt
adafruit_circuitpython_guvx_i2c-1.0.12.dist-info/RECORD
