Metadata-Version: 2.4
Name: adafruit-circuitpython-guvx-i2c
Version: 1.0.12
Summary: Python drivers for the GUVA-C32SM and GUVB-C31SM I2C UV sensors
Author-email: Adafruit Industries <circuitpython@adafruit.com>
License: MIT
Project-URL: Homepage, https://github.com/adafruit/Adafruit_CircuitPython_GUVX_I2C
Keywords: adafruit,blinka,circuitpython,micropython,guvx_i2c,UVA,UVB,Python,driver,I2C,GUVA,GUVB
Classifier: Intended Audience :: Developers
Classifier: Topic :: Software Development :: Libraries
Classifier: Topic :: Software Development :: Embedded Systems
Classifier: Topic :: System :: Hardware
Classifier: License :: OSI Approved :: MIT License
Classifier: Programming Language :: Python :: 3
License-File: LICENSE
Requires-Dist: Adafruit-Blinka
Requires-Dist: adafruit-circuitpython-busdevice
Requires-Dist: adafruit-circuitpython-register
Provides-Extra: optional
Requires-Dist: adafruit-circuitpython-debug-i2c; extra == "optional"
Dynamic: license-file
